LICENSE
MANIFEST.in
README.rst
setup.py
django_mynewsdesk.egg-info/PKG-INFO
django_mynewsdesk.egg-info/SOURCES.txt
django_mynewsdesk.egg-info/dependency_links.txt
django_mynewsdesk.egg-info/requires.txt
django_mynewsdesk.egg-info/top_level.txt
mynewsdesk/__init__.py
mynewsdesk/admin.py
mynewsdesk/api.py
mynewsdesk/models.py
mynewsdesk/sync.py
mynewsdesk/management/__init__.py
mynewsdesk/management/commands/__init__.py
mynewsdesk/management/commands/mynewsdesk_syncall.py
mynewsdesk/migrations/0001_initial.py
mynewsdesk/migrations/0002_auto_20150603_1034.py
mynewsdesk/migrations/__init__.py