Metadata-Version: 1.1
Name: django-mynewsdesk
Version: 0.5
Summary: Django package for MyNewsDesk API
Home-page: https://github.com/pkozlov/django-mynewsdesk
Author: Pavel Kozlov
Author-email: mail@pkozlov.ru
License: MIT License
Platform: UNKNOWN
Classifier: Environment :: Web Environment
Classifier: Framework :: Django
Classifier: Intended Audience :: Developers
Classifier: License :: OSI Approved :: MIT License
Classifier: Operating System :: OS Independent
Classifier: Programming Language :: Python
Classifier: Programming Language :: Python :: 2
Classifier: Programming Language :: Python :: 2.5
Classifier: Programming Language :: Python :: 2.7
Classifier: Topic :: Internet :: WWW/HTTP
Classifier: Topic :: Internet :: WWW/HTTP :: Dynamic Content
